test_juliano_image_processing/__init__.py
test_juliano_image_processing/processing/__init__.py
test_juliano_image_processing/processing/combination.py
test_juliano_image_processing/processing/transformation.py
test_juliano_image_processing/utils/__init__.py
test_juliano_image_processing/utils/io.py
test_juliano_image_processing/utils/plot.py
test_juliano_image_processing-0.0.1.dist-info/METADATA
test_juliano_image_processing-0.0.1.dist-info/WHEEL
test_juliano_image_processing-0.0.1.dist-info/top_level.txt
test_juliano_image_processing-0.0.1.dist-info/RECORD
